result/__init__.py
result/py.typed
result/result.py
python_result-0.2.1.dist-info/METADATA
python_result-0.2.1.dist-info/WHEEL
python_result-0.2.1.dist-info/top_level.txt
python_result-0.2.1.dist-info/RECORD
